<DataObject comparison="Ordinal">
  <Section id="">
    <Subsections>
      <Section id="General">
        <Subsections />
        <Entries>
          <Entry key="ElapsedTime">
            <double>11.7577927</double>
          </Entry>
          <Entry key="StartedAt">
            <dateTime>2024-06-12T21:01:00.6733368+03:00</dateTime>
          </Entry>
          <Entry key="EndedAt">
            <dateTime>2024-06-12T21:01:12.4311295+03:00</dateTime>
          </Entry>
          <Entry key="ReplayStatus">
            <LastReplayRunStatus>Passed</LastReplayRunStatus>
          </Entry>
          <Entry key="NumberOfReplayErrors">
            <int>0</int>
          </Entry>
          <Entry key="NumberOfReplayCriticalErrors">
            <int>0</int>
          </Entry>
          <Entry key="NumberOfCompilationErrors">
            <int>0</int>
          </Entry>
        </Entries>
      </Section>
    </Subsections>
    <Entries>
      <Entry key="Iterations">
        <int>1</int>
      </Entry>
    </Entries>
  </Section>
</DataObject>